openstudio_lib/__init__.py
openstudio_lib/__main__.py
openstudio_lib/events/__init__.py
openstudio_lib/events/event_producer.py
openstudio_lib/events/event_receiver.py
openstudio_lib/events/exchange_producer.py
openstudio_lib/events/exchange_receiver.py
openstudio_lib/logger/__init__.py
openstudio_lib/logger/logger_helper.py
openstudio_lib/workflow/__init__.py
openstudio_lib/workflow/workflow_helper.py
openstudio_lib-0.1.0.dist-info/METADATA
openstudio_lib-0.1.0.dist-info/WHEEL
openstudio_lib-0.1.0.dist-info/RECORD
