Metadata-Version: 2.1
Name: openstudio-lib
Version: 0.1.0
Summary: Simple and Flexible ML, DL, GAN and LLM workflow engine
Author: Kuluru Vineeth
Author-email: kuluruvineeth8623@gmail.com
Requires-Python: >=3.7,<4.0
Classifier: Programming Language :: Python :: 3
Classifier: Programming Language :: Python :: 3.7
Classifier: Programming Language :: Python :: 3.8
Classifier: Programming Language :: Python :: 3.9
Classifier: Programming Language :: Python :: 3.10
Classifier: Programming Language :: Python :: 3.11
Requires-Dist: pika (>=1.3.2,<2.0.0)
Requires-Dist: requests (>=2.31.0,<3.0.0)
